sortinghat/core/importer/backends/_version.py
sortinghat/core/importer/backends/eclipse.py
sortinghat_eclipse_foundation-0.2.3.dist-info/METADATA
sortinghat_eclipse_foundation-0.2.3.dist-info/WHEEL
sortinghat_eclipse_foundation-0.2.3.dist-info/licenses/AUTHORS
sortinghat_eclipse_foundation-0.2.3.dist-info/licenses/LICENSE.txt
sortinghat_eclipse_foundation-0.2.3.dist-info/RECORD
