Metadata-Version: 2.4
Name: sortinghat-eclipse-foundation
Version: 0.2.3
Summary: SortingHat backend to import identities from the Eclipse Foundation
License-File: AUTHORS
License-File: LICENSE.txt
Keywords: development,grimoirelab,sortinghat
Author: Bitergia Developers
Requires-Python: >=3.10,<4.0
Classifier: Development Status :: 4 - Beta
Classifier: Intended Audience :: Developers
Classifier: Intended Audience :: Science/Research
Classifier: Topic :: Software Development
Classifier: Programming Language :: Python :: 3
Requires-Dist: requests-oauth2client (>=1.7.0,<2.0.0)
Requires-Dist: sortinghat (>=1.10.0,<2.0.0)
